plasticscm/__about__.py
plasticscm/__init__.py
plasticscm/_plastic.py
plasticscm/config.py
plasticscm/exceptions.py
plasticscm/model.py
plasticscm/plasticscm.cfg
plasticscm/rest.py
plasticscm/util.py
plasticscm/v1/api.py
plasticscm/v1/model.py
plasticscm-0.5.0a1.dist-info/licenses/LICENSE
plasticscm-0.5.0a1.dist-info/METADATA
plasticscm-0.5.0a1.dist-info/WHEEL
plasticscm-0.5.0a1.dist-info/top_level.txt
plasticscm-0.5.0a1.dist-info/zip-safe
plasticscm-0.5.0a1.dist-info/RECORD
